MANIFEST.in
README.MD
conda_packages.yml
setup.py
ForceSpectroscopyHelperMCM/BayesSelector.py
ForceSpectroscopyHelperMCM/BayesianFit.py
ForceSpectroscopyHelperMCM/BayesianModel.py
ForceSpectroscopyHelperMCM/BayesianUtility.py
ForceSpectroscopyHelperMCM/__init__.py
ForceSpectroscopyHelperMCM/bayesConventor.py
ForceSpectroscopyHelperMCM/bayesData.py
ForceSpectroscopyHelperMCM/Utils/ConsoleColor.py
ForceSpectroscopyHelperMCM/Utils/Utility.py
ForceSpectroscopyHelperMCM/examples/startup.py
ForceSpectroscopyHelperMCM_mcm.egg-info/PKG-INFO
ForceSpectroscopyHelperMCM_mcm.egg-info/SOURCES.txt
ForceSpectroscopyHelperMCM_mcm.egg-info/dependency_links.txt
ForceSpectroscopyHelperMCM_mcm.egg-info/requires.txt
ForceSpectroscopyHelperMCM_mcm.egg-info/top_level.txt